project_root/__init__.py
src/__init__.py
project_root-0.3.0.dist-info/LICENSE
project_root-0.3.0.dist-info/METADATA
project_root-0.3.0.dist-info/WHEEL
project_root-0.3.0.dist-info/top_level.txt
project_root-0.3.0.dist-info/RECORD
